{"frames":[{"filename":"sprite1","frame":{"x":327,"y":0,"w":48,"h":32},"rotated":false,"trimmed":false,"spriteSourceSize":{"x":0,"y":0,"w":48,"h":32},"sourceSize":{"w":48,"h":32}},{"filename":"sprite2","frame":{"x":327,"y":33,"w":48,"h":32},"rotated":false,"trimmed":false,"spriteSourceSize":{"x":0,"y":0,"w":48,"h":32},"sourceSize":{"w":48,"h":32}},{"filename":"sprite3","frame":{"x":327,"y":66,"w":48,"h":32},"rotated":false,"trimmed":false,"spriteSourceSize":{"x":0,"y":0,"w":48,"h":32},"sourceSize":{"w":48,"h":32}},{"filename":"sprite4","frame":{"x":327,"y":99,"w":48,"h":32},"rotated":false,"trimmed":false,"spriteSourceSize":{"x":0,"y":0,"w":48,"h":32},"sourceSize":{"w":48,"h":32}},{"filename":"sprite5","frame":{"x":223,"y":136,"w":47,"h":34},"rotated":false,"trimmed":false,"spriteSourceSize":{"x":0,"y":0,"w":47,"h":34},"sourceSize":{"w":47,"h":34}},{"filename":"sprite6","frame":{"x":223,"y":171,"w":47,"h":34},"rotated":false,"trimmed":false,"spriteSourceSize":{"x":0,"y":0,"w":47,"h":34},"sourceSize":{"w":47,"h":34}},{"filename":"sprite7","frame":{"x":223,"y":206,"w":47,"h":34},"rotated":false,"trimmed":false,"spriteSourceSize":{"x":0,"y":0,"w":47,"h":34},"sourceSize":{"w":47,"h":34}},{"filename":"sprite8","frame":{"x":327,"y":228,"w":47,"h":30},"rotated":false,"trimmed":false,"spriteSourceSize":{"x":0,"y":0,"w":47,"h":30},"sourceSize":{"w":47,"h":30}},{"filename":"sprite9","frame":{"x":327,"y":259,"w":47,"h":30},"rotated":false,"trimmed":false,"spriteSourceSize":{"x":0,"y":0,"w":47,"h":30},"sourceSize":{"w":47,"h":30}},{"filename":"sprite10","frame":{"x":376,"y":93,"w":49,"h":30},"rotated":false,"trimmed":false,"spriteSourceSize":{"x":0,"y":0,"w":49,"h":30},"sourceSize":{"w":49,"h":30}},{"filename":"sprite11","frame":{"x":327,"y":290,"w":47,"h":30},"rotated":false,"trimmed":false,"spriteSourceSize":{"x":0,"y":0,"w":47,"h":30},"sourceSize":{"w":47,"h":30}},{"filename":"sprite12","frame":{"x":376,"y":124,"w":49,"h":30},"rotated":false,"trimmed":false,"spriteSourceSize":{"x":0,"y":0,"w":49,"h":30},"sourceSize":{"w":49,"h":30}},{"filename":"sprite13","frame":{"x":376,"y":155,"w":49,"h":30},"rotated":false,"trimmed":false,"spriteSourceSize":{"x":0,"y":0,"w":49,"h":30},"sourceSize":{"w":49,"h":30}},{"filename":"sprite14","frame":{"x":200,"y":375,"w":50,"h":30},"rotated":false,"trimmed":false,"spriteSourceSize":{"x":0,"y":0,"w":50,"h":30},"sourceSize":{"w":50,"h":30}},{"filename":"sprite15","frame":{"x":251,"y":375,"w":50,"h":30},"rotated":false,"trimmed":false,"spriteSourceSize":{"x":0,"y":0,"w":50,"h":30},"sourceSize":{"w":50,"h":30}},{"filename":"sprite16","frame":{"x":302,"y":375,"w":50,"h":30},"rotated":false,"trimmed":false,"spriteSourceSize":{"x":0,"y":0,"w":50,"h":30},"sourceSize":{"w":50,"h":30}},{"filename":"sprite17","frame":{"x":223,"y":0,"w":49,"h":33},"rotated":false,"trimmed":false,"spriteSourceSize":{"x":0,"y":0,"w":49,"h":33},"sourceSize":{"w":49,"h":33}},{"filename":"sprite18","frame":{"x":223,"y":34,"w":49,"h":33},"rotated":false,"trimmed":false,"spriteSourceSize":{"x":0,"y":0,"w":49,"h":33},"sourceSize":{"w":49,"h":33}},{"filename":"sprite19","frame":{"x":223,"y":68,"w":49,"h":33},"rotated":false,"trimmed":false,"spriteSourceSize":{"x":0,"y":0,"w":49,"h":33},"sourceSize":{"w":49,"h":33}},{"filename":"sprite20","frame":{"x":223,"y":102,"w":49,"h":33},"rotated":false,"trimmed":false,"spriteSourceSize":{"x":0,"y":0,"w":49,"h":33},"sourceSize":{"w":49,"h":33}},{"filename":"sprite21","frame":{"x":327,"y":132,"w":48,"h":31},"rotated":false,"trimmed":false,"spriteSourceSize":{"x":0,"y":0,"w":48,"h":31},"sourceSize":{"w":48,"h":31}},{"filename":"sprite22","frame":{"x":327,"y":164,"w":48,"h":31},"rotated":false,"trimmed":false,"spriteSourceSize":{"x":0,"y":0,"w":48,"h":31},"sourceSize":{"w":48,"h":31}},{"filename":"sprite23","frame":{"x":327,"y":196,"w":48,"h":31},"rotated":false,"trimmed":false,"spriteSourceSize":{"x":0,"y":0,"w":48,"h":31},"sourceSize":{"w":48,"h":31}},{"filename":"sprite24","frame":{"x":0,"y":96,"w":55,"h":30},"rotated":false,"trimmed":false,"spriteSourceSize":{"x":0,"y":0,"w":55,"h":30},"sourceSize":{"w":55,"h":30}},{"filename":"sprite25","frame":{"x":0,"y":127,"w":55,"h":30},"rotated":false,"trimmed":false,"spriteSourceSize":{"x":0,"y":0,"w":55,"h":30},"sourceSize":{"w":55,"h":30}},{"filename":"sprite26","frame":{"x":0,"y":0,"w":54,"h":31},"rotated":false,"trimmed":false,"spriteSourceSize":{"x":0,"y":0,"w":54,"h":31},"sourceSize":{"w":54,"h":31}},{"filename":"sprite27","frame":{"x":327,"y":321,"w":47,"h":30},"rotated":false,"trimmed":false,"spriteSourceSize":{"x":0,"y":0,"w":47,"h":30},"sourceSize":{"w":47,"h":30}},{"filename":"sprite28","frame":{"x":0,"y":375,"w":49,"h":31},"rotated":false,"trimmed":false,"spriteSourceSize":{"x":0,"y":0,"w":49,"h":31},"sourceSize":{"w":49,"h":31}},{"filename":"sprite29","frame":{"x":50,"y":375,"w":49,"h":31},"rotated":false,"trimmed":false,"spriteSourceSize":{"x":0,"y":0,"w":49,"h":31},"sourceSize":{"w":49,"h":31}},{"filename":"sprite30","frame":{"x":110,"y":0,"w":55,"h":30},"rotated":false,"trimmed":false,"spriteSourceSize":{"x":0,"y":0,"w":55,"h":30},"sourceSize":{"w":55,"h":30}},{"filename":"sprite31","frame":{"x":0,"y":32,"w":54,"h":31},"rotated":false,"trimmed":false,"spriteSourceSize":{"x":0,"y":0,"w":54,"h":31},"sourceSize":{"w":54,"h":31}},{"filename":"sprite32","frame":{"x":0,"y":64,"w":54,"h":31},"rotated":false,"trimmed":false,"spriteSourceSize":{"x":0,"y":0,"w":54,"h":31},"sourceSize":{"w":54,"h":31}},{"filename":"sprite33","frame":{"x":56,"y":127,"w":53,"h":30},"rotated":false,"trimmed":false,"spriteSourceSize":{"x":0,"y":0,"w":53,"h":30},"sourceSize":{"w":53,"h":30}},{"filename":"sprite34","frame":{"x":56,"y":96,"w":53,"h":30},"rotated":false,"trimmed":false,"spriteSourceSize":{"x":0,"y":0,"w":53,"h":30},"sourceSize":{"w":53,"h":30}},{"filename":"sprite35","frame":{"x":110,"y":31,"w":55,"h":30},"rotated":false,"trimmed":false,"spriteSourceSize":{"x":0,"y":0,"w":55,"h":30},"sourceSize":{"w":55,"h":30}},{"filename":"sprite36","frame":{"x":110,"y":62,"w":55,"h":30},"rotated":false,"trimmed":false,"spriteSourceSize":{"x":0,"y":0,"w":55,"h":30},"sourceSize":{"w":55,"h":30}},{"filename":"sprite37","frame":{"x":55,"y":0,"w":54,"h":31},"rotated":false,"trimmed":false,"spriteSourceSize":{"x":0,"y":0,"w":54,"h":31},"sourceSize":{"w":54,"h":31}},{"filename":"sprite38","frame":{"x":55,"y":32,"w":54,"h":31},"rotated":false,"trimmed":false,"spriteSourceSize":{"x":0,"y":0,"w":54,"h":31},"sourceSize":{"w":54,"h":31}},{"filename":"sprite39","frame":{"x":376,"y":279,"w":47,"h":30},"rotated":false,"trimmed":false,"spriteSourceSize":{"x":0,"y":0,"w":47,"h":30},"sourceSize":{"w":47,"h":30}},{"filename":"sprite40","frame":{"x":376,"y":310,"w":47,"h":30},"rotated":false,"trimmed":false,"spriteSourceSize":{"x":0,"y":0,"w":47,"h":30},"sourceSize":{"w":47,"h":30}},{"filename":"sprite41","frame":{"x":100,"y":375,"w":49,"h":31},"rotated":false,"trimmed":false,"spriteSourceSize":{"x":0,"y":0,"w":49,"h":31},"sourceSize":{"w":49,"h":31}},{"filename":"sprite42","frame":{"x":150,"y":375,"w":49,"h":31},"rotated":false,"trimmed":false,"spriteSourceSize":{"x":0,"y":0,"w":49,"h":31},"sourceSize":{"w":49,"h":31}},{"filename":"sprite43","frame":{"x":110,"y":93,"w":55,"h":30},"rotated":false,"trimmed":false,"spriteSourceSize":{"x":0,"y":0,"w":55,"h":30},"sourceSize":{"w":55,"h":30}},{"filename":"sprite44","frame":{"x":110,"y":124,"w":55,"h":30},"rotated":false,"trimmed":false,"spriteSourceSize":{"x":0,"y":0,"w":55,"h":30},"sourceSize":{"w":55,"h":30}},{"filename":"sprite45","frame":{"x":55,"y":64,"w":54,"h":31},"rotated":false,"trimmed":false,"spriteSourceSize":{"x":0,"y":0,"w":54,"h":31},"sourceSize":{"w":54,"h":31}},{"filename":"sprite46","frame":{"x":273,"y":0,"w":53,"h":30},"rotated":false,"trimmed":false,"spriteSourceSize":{"x":0,"y":0,"w":53,"h":30},"sourceSize":{"w":53,"h":30}},{"filename":"sprite47","frame":{"x":273,"y":31,"w":53,"h":30},"rotated":false,"trimmed":false,"spriteSourceSize":{"x":0,"y":0,"w":53,"h":30},"sourceSize":{"w":53,"h":30}},{"filename":"sprite48","frame":{"x":0,"y":248,"w":52,"h":31},"rotated":false,"trimmed":false,"spriteSourceSize":{"x":0,"y":0,"w":52,"h":31},"sourceSize":{"w":52,"h":31}},{"filename":"sprite49","frame":{"x":53,"y":248,"w":52,"h":31},"rotated":false,"trimmed":false,"spriteSourceSize":{"x":0,"y":0,"w":52,"h":31},"sourceSize":{"w":52,"h":31}},{"filename":"sprite50","frame":{"x":114,"y":218,"w":47,"h":29},"rotated":false,"trimmed":false,"spriteSourceSize":{"x":0,"y":0,"w":47,"h":29},"sourceSize":{"w":47,"h":29}},{"filename":"sprite51","frame":{"x":162,"y":218,"w":47,"h":29},"rotated":false,"trimmed":false,"spriteSourceSize":{"x":0,"y":0,"w":47,"h":29},"sourceSize":{"w":47,"h":29}},{"filename":"sprite52","frame":{"x":376,"y":0,"w":50,"h":30},"rotated":false,"trimmed":false,"spriteSourceSize":{"x":0,"y":0,"w":50,"h":30},"sourceSize":{"w":50,"h":30}},{"filename":"sprite53","frame":{"x":106,"y":248,"w":52,"h":31},"rotated":false,"trimmed":false,"spriteSourceSize":{"x":0,"y":0,"w":52,"h":31},"sourceSize":{"w":52,"h":31}},{"filename":"sprite54","frame":{"x":159,"y":248,"w":52,"h":31},"rotated":false,"trimmed":false,"spriteSourceSize":{"x":0,"y":0,"w":52,"h":31},"sourceSize":{"w":52,"h":31}},{"filename":"sprite55","frame":{"x":212,"y":248,"w":52,"h":31},"rotated":false,"trimmed":false,"spriteSourceSize":{"x":0,"y":0,"w":52,"h":31},"sourceSize":{"w":52,"h":31}},{"filename":"sprite56","frame":{"x":114,"y":188,"w":47,"h":29},"rotated":false,"trimmed":false,"spriteSourceSize":{"x":0,"y":0,"w":47,"h":29},"sourceSize":{"w":47,"h":29}},{"filename":"sprite57","frame":{"x":114,"y":158,"w":47,"h":29},"rotated":false,"trimmed":false,"spriteSourceSize":{"x":0,"y":0,"w":47,"h":29},"sourceSize":{"w":47,"h":29}},{"filename":"sprite58","frame":{"x":376,"y":31,"w":50,"h":30},"rotated":false,"trimmed":false,"spriteSourceSize":{"x":0,"y":0,"w":50,"h":30},"sourceSize":{"w":50,"h":30}},{"filename":"sprite59","frame":{"x":376,"y":62,"w":50,"h":30},"rotated":false,"trimmed":false,"spriteSourceSize":{"x":0,"y":0,"w":50,"h":30},"sourceSize":{"w":50,"h":30}},{"filename":"sprite60","frame":{"x":0,"y":280,"w":52,"h":31},"rotated":false,"trimmed":false,"spriteSourceSize":{"x":0,"y":0,"w":52,"h":31},"sourceSize":{"w":52,"h":31}},{"filename":"sprite61","frame":{"x":53,"y":280,"w":52,"h":31},"rotated":false,"trimmed":false,"spriteSourceSize":{"x":0,"y":0,"w":52,"h":31},"sourceSize":{"w":52,"h":31}},{"filename":"sprite62","frame":{"x":0,"y":158,"w":56,"h":29},"rotated":false,"trimmed":false,"spriteSourceSize":{"x":0,"y":0,"w":56,"h":29},"sourceSize":{"w":56,"h":29}},{"filename":"sprite63","frame":{"x":57,"y":158,"w":56,"h":29},"rotated":false,"trimmed":false,"spriteSourceSize":{"x":0,"y":0,"w":56,"h":29},"sourceSize":{"w":56,"h":29}},{"filename":"sprite64","frame":{"x":0,"y":188,"w":56,"h":29},"rotated":false,"trimmed":false,"spriteSourceSize":{"x":0,"y":0,"w":56,"h":29},"sourceSize":{"w":56,"h":29}},{"filename":"sprite65","frame":{"x":57,"y":188,"w":56,"h":29},"rotated":false,"trimmed":false,"spriteSourceSize":{"x":0,"y":0,"w":56,"h":29},"sourceSize":{"w":56,"h":29}},{"filename":"sprite66","frame":{"x":166,"y":0,"w":56,"h":29},"rotated":false,"trimmed":false,"spriteSourceSize":{"x":0,"y":0,"w":56,"h":29},"sourceSize":{"w":56,"h":29}},{"filename":"sprite67","frame":{"x":166,"y":30,"w":56,"h":29},"rotated":false,"trimmed":false,"spriteSourceSize":{"x":0,"y":0,"w":56,"h":29},"sourceSize":{"w":56,"h":29}},{"filename":"sprite68","frame":{"x":166,"y":60,"w":56,"h":29},"rotated":false,"trimmed":false,"spriteSourceSize":{"x":0,"y":0,"w":56,"h":29},"sourceSize":{"w":56,"h":29}},{"filename":"sprite69","frame":{"x":166,"y":90,"w":56,"h":29},"rotated":false,"trimmed":false,"spriteSourceSize":{"x":0,"y":0,"w":56,"h":29},"sourceSize":{"w":56,"h":29}},{"filename":"sprite70","frame":{"x":273,"y":155,"w":52,"h":30},"rotated":false,"trimmed":false,"spriteSourceSize":{"x":0,"y":0,"w":52,"h":30},"sourceSize":{"w":52,"h":30}},{"filename":"sprite71","frame":{"x":273,"y":186,"w":52,"h":30},"rotated":false,"trimmed":false,"spriteSourceSize":{"x":0,"y":0,"w":52,"h":30},"sourceSize":{"w":52,"h":30}},{"filename":"sprite72","frame":{"x":166,"y":120,"w":56,"h":29},"rotated":false,"trimmed":false,"spriteSourceSize":{"x":0,"y":0,"w":56,"h":29},"sourceSize":{"w":56,"h":29}},{"filename":"sprite73","frame":{"x":166,"y":150,"w":56,"h":29},"rotated":false,"trimmed":false,"spriteSourceSize":{"x":0,"y":0,"w":56,"h":29},"sourceSize":{"w":56,"h":29}},{"filename":"sprite74","frame":{"x":273,"y":217,"w":52,"h":30},"rotated":false,"trimmed":false,"spriteSourceSize":{"x":0,"y":0,"w":52,"h":30},"sourceSize":{"w":52,"h":30}},{"filename":"sprite75","frame":{"x":166,"y":180,"w":56,"h":29},"rotated":false,"trimmed":false,"spriteSourceSize":{"x":0,"y":0,"w":56,"h":29},"sourceSize":{"w":56,"h":29}},{"filename":"sprite76","frame":{"x":0,"y":218,"w":56,"h":29},"rotated":false,"trimmed":false,"spriteSourceSize":{"x":0,"y":0,"w":56,"h":29},"sourceSize":{"w":56,"h":29}},{"filename":"sprite77","frame":{"x":273,"y":248,"w":52,"h":30},"rotated":false,"trimmed":false,"spriteSourceSize":{"x":0,"y":0,"w":52,"h":30},"sourceSize":{"w":52,"h":30}},{"filename":"sprite78","frame":{"x":273,"y":279,"w":52,"h":30},"rotated":false,"trimmed":false,"spriteSourceSize":{"x":0,"y":0,"w":52,"h":30},"sourceSize":{"w":52,"h":30}},{"filename":"sprite79","frame":{"x":57,"y":218,"w":56,"h":29},"rotated":false,"trimmed":false,"spriteSourceSize":{"x":0,"y":0,"w":56,"h":29},"sourceSize":{"w":56,"h":29}},{"filename":"sprite80","frame":{"x":0,"y":312,"w":52,"h":30},"rotated":false,"trimmed":false,"spriteSourceSize":{"x":0,"y":0,"w":52,"h":30},"sourceSize":{"w":52,"h":30}},{"filename":"sprite81","frame":{"x":53,"y":312,"w":52,"h":30},"rotated":false,"trimmed":false,"spriteSourceSize":{"x":0,"y":0,"w":52,"h":30},"sourceSize":{"w":52,"h":30}},{"filename":"sprite82","frame":{"x":0,"y":343,"w":50,"h":31},"rotated":false,"trimmed":false,"spriteSourceSize":{"x":0,"y":0,"w":50,"h":31},"sourceSize":{"w":50,"h":31}},{"filename":"sprite83","frame":{"x":376,"y":186,"w":49,"h":30},"rotated":false,"trimmed":false,"spriteSourceSize":{"x":0,"y":0,"w":49,"h":30},"sourceSize":{"w":49,"h":30}},{"filename":"sprite84","frame":{"x":376,"y":217,"w":49,"h":30},"rotated":false,"trimmed":false,"spriteSourceSize":{"x":0,"y":0,"w":49,"h":30},"sourceSize":{"w":49,"h":30}},{"filename":"sprite85","frame":{"x":273,"y":62,"w":53,"h":30},"rotated":false,"trimmed":false,"spriteSourceSize":{"x":0,"y":0,"w":53,"h":30},"sourceSize":{"w":53,"h":30}},{"filename":"sprite86","frame":{"x":273,"y":93,"w":53,"h":30},"rotated":false,"trimmed":false,"spriteSourceSize":{"x":0,"y":0,"w":53,"h":30},"sourceSize":{"w":53,"h":30}},{"filename":"sprite87","frame":{"x":51,"y":343,"w":50,"h":31},"rotated":false,"trimmed":false,"spriteSourceSize":{"x":0,"y":0,"w":50,"h":31},"sourceSize":{"w":50,"h":31}},{"filename":"sprite88","frame":{"x":102,"y":343,"w":50,"h":31},"rotated":false,"trimmed":false,"spriteSourceSize":{"x":0,"y":0,"w":50,"h":31},"sourceSize":{"w":50,"h":31}},{"filename":"sprite89","frame":{"x":376,"y":248,"w":49,"h":30},"rotated":false,"trimmed":false,"spriteSourceSize":{"x":0,"y":0,"w":49,"h":30},"sourceSize":{"w":49,"h":30}},{"filename":"sprite90","frame":{"x":273,"y":124,"w":53,"h":30},"rotated":false,"trimmed":false,"spriteSourceSize":{"x":0,"y":0,"w":53,"h":30},"sourceSize":{"w":53,"h":30}},{"filename":"sprite91","frame":{"x":106,"y":280,"w":57,"h":28},"rotated":false,"trimmed":false,"spriteSourceSize":{"x":0,"y":0,"w":57,"h":28},"sourceSize":{"w":57,"h":28}},{"filename":"sprite92","frame":{"x":153,"y":343,"w":55,"h":28},"rotated":false,"trimmed":false,"spriteSourceSize":{"x":0,"y":0,"w":55,"h":28},"sourceSize":{"w":55,"h":28}},{"filename":"sprite93","frame":{"x":209,"y":343,"w":55,"h":28},"rotated":false,"trimmed":false,"spriteSourceSize":{"x":0,"y":0,"w":55,"h":28},"sourceSize":{"w":55,"h":28}},{"filename":"sprite94","frame":{"x":164,"y":280,"w":57,"h":28},"rotated":false,"trimmed":false,"spriteSourceSize":{"x":0,"y":0,"w":57,"h":28},"sourceSize":{"w":57,"h":28}},{"filename":"sprite95","frame":{"x":265,"y":343,"w":55,"h":28},"rotated":false,"trimmed":false,"spriteSourceSize":{"x":0,"y":0,"w":55,"h":28},"sourceSize":{"w":55,"h":28}},{"filename":"sprite97","frame":{"x":106,"y":312,"w":55,"h":28},"rotated":false,"trimmed":false,"spriteSourceSize":{"x":0,"y":0,"w":55,"h":28},"sourceSize":{"w":55,"h":28}},{"filename":"sprite98","frame":{"x":162,"y":312,"w":55,"h":28},"rotated":false,"trimmed":false,"spriteSourceSize":{"x":0,"y":0,"w":55,"h":28},"sourceSize":{"w":55,"h":28}},{"filename":"sprite100","frame":{"x":218,"y":312,"w":55,"h":28},"rotated":false,"trimmed":false,"spriteSourceSize":{"x":0,"y":0,"w":55,"h":28},"sourceSize":{"w":55,"h":28}},{"filename":"sprite101","frame":{"x":274,"y":312,"w":50,"h":25},"rotated":false,"trimmed":false,"spriteSourceSize":{"x":0,"y":0,"w":50,"h":25},"sourceSize":{"w":50,"h":25}},{"filename":"sprite102","frame":{"x":222,"y":280,"w":50,"h":25},"rotated":false,"trimmed":false,"spriteSourceSize":{"x":0,"y":0,"w":50,"h":25},"sourceSize":{"w":50,"h":25}},{"filename":"sprite103","frame":{"x":376,"y":341,"w":50,"h":25},"rotated":false,"trimmed":false,"spriteSourceSize":{"x":0,"y":0,"w":50,"h":25},"sourceSize":{"w":50,"h":25}}],"meta":{"app":"https://www.leshylabs.com/apps/sstool/","version":"Leshy SpriteSheet Tool v0.8.4","image":"geodude_back.png","size":{"w":426,"h":406},"scale":1}}